.buildpacks
.documentup.json
.travis.yml
Gemfile
Gemfile.lock
Processes
Procfile
README.md
UNLICENSE
alembic.ini
drive.py
gunicorn_config.py
pip_install.sh
requirements.txt
run.sh
runtime.txt
setup.py
/Users/thruflo/Development/ntorque/.buildpacks
/Users/thruflo/Development/ntorque/.documentup.json
/Users/thruflo/Development/ntorque/.travis.yml
/Users/thruflo/Development/ntorque/Gemfile
/Users/thruflo/Development/ntorque/Gemfile.lock
/Users/thruflo/Development/ntorque/Processes
/Users/thruflo/Development/ntorque/Procfile
/Users/thruflo/Development/ntorque/README.md
/Users/thruflo/Development/ntorque/UNLICENSE
/Users/thruflo/Development/ntorque/alembic.ini
/Users/thruflo/Development/ntorque/drive.py
/Users/thruflo/Development/ntorque/gunicorn_config.py
/Users/thruflo/Development/ntorque/pip_install.sh
/Users/thruflo/Development/ntorque/requirements.txt
/Users/thruflo/Development/ntorque/run.sh
/Users/thruflo/Development/ntorque/runtime.txt
/Users/thruflo/Development/ntorque/setup.py
/Users/thruflo/Development/ntorque/alembic/env.py
/Users/thruflo/Development/ntorque/alembic/script.py.mako
/Users/thruflo/Development/ntorque/alembic/scripts/create_application.py
/Users/thruflo/Development/ntorque/alembic/versions/32ee88d6d6d_.py
/Users/thruflo/Development/ntorque/alembic/versions/4ae58a31c179_.py
/Users/thruflo/Development/ntorque/src/ntorque/__init__.py
/Users/thruflo/Development/ntorque/src/ntorque/backoff.py
/Users/thruflo/Development/ntorque/src/ntorque/client.py
/Users/thruflo/Development/ntorque/src/ntorque/root.py
/Users/thruflo/Development/ntorque/src/ntorque/util.py
/Users/thruflo/Development/ntorque/src/ntorque/api/__init__.py
/Users/thruflo/Development/ntorque/src/ntorque/api/auth.py
/Users/thruflo/Development/ntorque/src/ntorque/api/exc.py
/Users/thruflo/Development/ntorque/src/ntorque/api/rate.py
/Users/thruflo/Development/ntorque/src/ntorque/api/tree.py
/Users/thruflo/Development/ntorque/src/ntorque/api/view.py
src/ntorque.egg-info/PKG-INFO
src/ntorque.egg-info/SOURCES.txt
src/ntorque.egg-info/dependency_links.txt
src/ntorque.egg-info/entry_points.txt
src/ntorque.egg-info/top_level.txt
src/ntorque.egg-info/zip-safe
