Metadata-Version: 1.1
Name: ntorque
Version: 0.3
Summary: Web hook task queue service.
Home-page: http://ntorque.com
Author: James Arthur
Author-email: username: thruflo, domain: gmail.com
License: This is free and unencumbered software released into the public domain.
